dewloosh/mpl/__init__.py
dewloosh/mpl/d2.py
dewloosh/mpl/parallel.py
dewloosh/mpl/triplot.py
dewloosh/mpl/utils.py
dewloosh.mpl-0.0.6.dist-info/LICENSE
dewloosh.mpl-0.0.6.dist-info/METADATA
dewloosh.mpl-0.0.6.dist-info/WHEEL
dewloosh.mpl-0.0.6.dist-info/top_level.txt
dewloosh.mpl-0.0.6.dist-info/RECORD
