Metadata-Version: 2.1
Name: dewloosh.mpl
Version: 0.0.6
Summary: Domain spceific data visualization with matplotlib.
Home-page: https://github.com/dewloosh/dewloosh-mpl
Download-URL: https://github.com/dewloosh/dewloosh-mpl/archive/refs/tags/0.0.6.zip
Author: Bence Balogh
Author-email: dewloosh@gmail.com
Classifier: Development Status :: 5 - Production/Stable
Classifier: License :: OSI Approved :: MIT License
Classifier: Programming Language :: Python :: 3.7
Classifier: Programming Language :: Python :: 3.8
Classifier: Programming Language :: Python :: 3.9
Classifier: Programming Language :: Python :: 3.10
Classifier: Programming Language :: Python :: 3 :: Only
Classifier: Operating System :: OS Independent
Requires-Python: >=3.7, <3.11
License-File: LICENSE
Requires-Dist: setuptools (>=65.5.1)
Requires-Dist: wheel (>=0.38.0)
Requires-Dist: linkeddeepdict (>=0.0.1)
Requires-Dist: polymesh (>=0.0.14)
Requires-Dist: matplotlib
